asymcrypt/__init__.py
asymcrypt-0.0.10.data/scripts/asymdecrypt
asymcrypt-0.0.10.data/scripts/asymencrypt
asymcrypt-0.0.10.data/scripts/asymgenkeys
asymcrypt-0.0.10.dist-info/DESCRIPTION.rst
asymcrypt-0.0.10.dist-info/METADATA
asymcrypt-0.0.10.dist-info/RECORD
asymcrypt-0.0.10.dist-info/WHEEL
asymcrypt-0.0.10.dist-info/metadata.json
asymcrypt-0.0.10.dist-info/top_level.txt
