Metadata-Version: 2.0
Name: asymcrypt
Version: 0.0.10
Summary: Super easy asymmetric encryption for python
Home-page: https://github.com/elapouya/python-asymcrypt
Author: Eric Lapouyade
Author-email: elapouya@gmail.com
License: LGPL 2.1
Keywords: encrypt
Platform: UNKNOWN
Classifier: Intended Audience :: Developers
Classifier: Development Status :: 4 - Beta
Classifier: Programming Language :: Python :: 2
Classifier: Programming Language :: Python :: 2.7
Classifier: Programming Language :: Python :: 3
Classifier: Programming Language :: Python :: 3.4
Requires-Dist: pycryptodome
